{"OpenedDocuments":"[]","ProjectBreakpoints":"{\"Value\":{\"SAP/CreatePivotTable.xaml\":[{\"ConditionalExpression\":null,\"ActionExpression\":null,\"ExpectedHitCounter\":null,\"ShouldContinueAfterAction\":false,\"IsEnabled\":true,\"ActivityIdRef\":\"Assign_6\",\"ActivityId\":\"1.3\",\"ActivityName\":\"Assign\"}]}}","ProjectWatches":"{\"Value\":[]}","LibraryProjectSettings":"{\"IncludeSourcesByDefault\":true,\"UseCompilerV2\":false,\"CompileExpressions\":true,\"DefaultActivitiesRootCategories\":[null]}"}